Metadata-Version: 2.1
Name: nonebot-plugin-repeater2
Version: 0.1.0
Summary: Auto +1 in groups.
License: MIT
Author: KafCoppelia
Author-email: k740677208@gmail.com
Requires-Python: >=3.7.3,<4.0.0
Classifier: License :: OSI Approved :: MIT License
Classifier: Programming Language :: Python :: 3
Classifier: Programming Language :: Python :: 3.10
Classifier: Programming Language :: Python :: 3.8
Classifier: Programming Language :: Python :: 3.9
Requires-Dist: nonebot-adapter-onebot (>=2.0.0-beta.1,<3.0.0)
Requires-Dist: nonebot2 (>=2.0.0-beta.2,<3.0.0)
